brr/__init__.py
brr/braille_renderer.py
brr-0.2.0.dist-info/entry_points.txt
brr-0.2.0.dist-info/LICENSE
brr-0.2.0.dist-info/WHEEL
brr-0.2.0.dist-info/METADATA
brr-0.2.0.dist-info/RECORD
