Metadata-Version: 2.1
Name: brr
Version: 0.2.0
Summary: terminal image renderer using braille characters in true color
License: GPL-3.0-or-later
Author: jeppetp
Author-email: jepptp@gmail.com
Requires-Python: >=3.10,<4.0
Classifier: License :: OSI Approved :: GNU General Public License v3 or later (GPLv3+)
Classifier: Programming Language :: Python :: 3
Classifier: Programming Language :: Python :: 3.10
Requires-Dist: Pillow (==9.2.0)
Requires-Dist: click (==8.1.3)
